graypy/__init__.py
graypy/handler.py
graypy/rabbitmq.py
tests/__init__.py
tests/helper.py
tests/config/create_ssl_certs.sh
tests/config/docker-compose.yml
tests/config/inputs.json
tests/config/start_local_graylog_server.sh
tests/config/stop_local_graylog_server.sh
tests/integration/__init__.py
tests/integration/helper.py
tests/integration/test_chunked_logging.py
tests/integration/test_common_logging.py
tests/integration/test_debugging_fields.py
tests/integration/test_extra_fields.py
tests/integration/test_status_issue.py
tests/unit/__init__.py
tests/unit/helper.py
tests/unit/test_ExcludeFilter.py
tests/unit/test_GELFRabbitHandler.py
tests/unit/test_chunking.py
tests/unit/test_handler.py
graypy-2.0.0.dist-info/LICENSE
graypy-2.0.0.dist-info/METADATA
graypy-2.0.0.dist-info/WHEEL
graypy-2.0.0.dist-info/top_level.txt
graypy-2.0.0.dist-info/RECORD
