Metadata-Version: 2.1
Name: graypy
Version: 2.0.0
Summary: Python logging handlers that send messages in the Graylog Extended Log Format (GELF).
Home-page: https://github.com/severb/graypy
Author: Sever Banesiu
Author-email: banesiu.sever@gmail.com
License: BSD License
Keywords: logging gelf graylog2 graylog udp amqp
Platform: UNKNOWN
Classifier: License :: OSI Approved :: BSD License
Classifier: Intended Audience :: Developers
Classifier: Programming Language :: Python
Classifier: Programming Language :: Python :: 2
Classifier: Programming Language :: Python :: 2.7
Classifier: Programming Language :: Python :: 3
Classifier: Programming Language :: Python :: 3.2
Classifier: Programming Language :: Python :: 3.3
Classifier: Programming Language :: Python :: 3.4
Classifier: Programming Language :: Python :: 3.5
Classifier: Programming Language :: Python :: 3.6
Classifier: Programming Language :: Python :: 3.7
Classifier: Programming Language :: Python :: Implementation :: CPython
Classifier: Programming Language :: Python :: Implementation :: PyPy
Classifier: Topic :: System :: Logging
Provides-Extra: amqp
Requires-Dist: amqplib (==1.0.2) ; extra == 'amqp'
Provides-Extra: docs
Requires-Dist: sphinx (<3.0.0,>=2.1.2) ; extra == 'docs'
Requires-Dist: sphinx-rtd-theme (<1.0.0,>=0.4.3) ; extra == 'docs'
Requires-Dist: sphinx-autodoc-typehints (<2.0.0,>=1.6.0) ; extra == 'docs'
